{
    "id": 2204820,
    "type": 2,
    "seed": {
        "id": "m722tpqqh60suew3",
        "overworld": "RUINED_PORTAL",
        "nether": "STABLES",
        "endTowers": [
            100,
            82,
            79,
            94
        ],
        "variations": [
            "type:structure:completable",
            "biome:structure:forest",
            "type:structure:completable",
            "biome:structure:forest",
            "bastion:good_gap:1",
            "bastion:triple:1",
            "bastion:single:1",
            "bastion:small_single:1",
            "biome:bastion:soul_sand_valley",
            "biome:fortress:crimson_forest",
            "end_spawn:buried:57",
            "end_tower:caged:front_center",
            "end_tower:caged:back"
        ]
    },
    "category": "ANY",
    "gameMode": "default",
    "players": [
        {
            "uuid": "34c876e4a23a4fe5a1fbf76a41db0e78",
            "nickname": "LazarBim",
            "roleType": 0,
            "eloRate": 1635,
            "eloRank": 89,
            "country": "us"
        },
        {
            "uuid": "b516d1d18261467bbb6f447f0c111be7",
            "nickname": "Gabryll_",
            "roleType": 0,
            "eloRate": 1472,
            "eloRank": 226,
            "country": "pl"
        }
    ],
    "spectators": [],
    "result": {
        "uuid": "34c876e4a23a4fe5a1fbf76a41db0e78",
        "time": 416619
    },
    "forfeited": true,
    "decayed": false,
    "rank": {
        "season": null,
        "allTime": null
    },
    "vod": [],
    "changes": [
        {
            "uuid": "34c876e4a23a4fe5a1fbf76a41db0e78",
            "change": 15,
            "eloRate": 1621
        },
        {
            "uuid": "b516d1d18261467bbb6f447f0c111be7",
            "change": -15,
            "eloRate": 1467
        }
    ],
    "completions": [],
    "timelines": [
        {
            "uuid": "b516d1d18261467bbb6f447f0c111be7",
            "time": 416618,
            "type": "projectelo.timeline.forfeit"
        },
        {
            "uuid": "b516d1d18261467bbb6f447f0c111be7",
            "time": 407476,
            "type": "projectelo.timeline.death"
        },
        {
            "uuid": "34c876e4a23a4fe5a1fbf76a41db0e78",
            "time": 387520,
            "type": "nether.find_fortress"
        },
        {
            "uuid": "34c876e4a23a4fe5a1fbf76a41db0e78",
            "time": 371572,
            "type": "nether.obtain_blaze_rod"
        },
        {
            "uuid": "b516d1d18261467bbb6f447f0c111be7",
            "time": 363123,
            "type": "nether.obtain_blaze_rod"
        },
        {
            "uuid": "b516d1d18261467bbb6f447f0c111be7",
            "time": 360645,
            "type": "adventure.kill_a_mob"
        },
        {
            "uuid": "b516d1d18261467bbb6f447f0c111be7",
            "time": 358966,
            "type": "nether.find_fortress"
        },
        {
            "uuid": "34c876e4a23a4fe5a1fbf76a41db0e78",
            "time": 339069,
            "type": "story.obtain_armor"
        },
        {
            "uuid": "b516d1d18261467bbb6f447f0c111be7",
            "time": 320167,
            "type": "story.obtain_armor"
        },
        {
            "uuid": "34c876e4a23a4fe5a1fbf76a41db0e78",
            "time": 286275,
            "type": "story.smelt_iron"
        },
        {
            "uuid": "b516d1d18261467bbb6f447f0c111be7",
            "time": 264768,
            "type": "nether.obtain_crying_obsidian"
        },
        {
            "uuid": "b516d1d18261467bbb6f447f0c111be7",
            "time": 179268,
            "type": "husbandry.root"
        },
        {
            "uuid": "34c876e4a23a4fe5a1fbf76a41db0e78",
            "time": 155833,
            "type": "nether.obtain_crying_obsidian"
        },
        {
            "uuid": "34c876e4a23a4fe5a1fbf76a41db0e78",
            "time": 153948,
            "type": "nether.loot_bastion"
        },
        {
            "uuid": "34c876e4a23a4fe5a1fbf76a41db0e78",
            "time": 152486,
            "type": "husbandry.root"
        },
        {
            "uuid": "34c876e4a23a4fe5a1fbf76a41db0e78",
            "time": 149599,
            "type": "adventure.kill_a_mob"
        },
        {
            "uuid": "b516d1d18261467bbb6f447f0c111be7",
            "time": 143440,
            "type": "nether.loot_bastion"
        },
        {
            "uuid": "b516d1d18261467bbb6f447f0c111be7",
            "time": 137971,
            "type": "nether.find_bastion"
        },
        {
            "uuid": "34c876e4a23a4fe5a1fbf76a41db0e78",
            "time": 127536,
            "type": "nether.find_bastion"
        },
        {
            "uuid": "b516d1d18261467bbb6f447f0c111be7",
            "time": 102214,
            "type": "story.enter_the_nether"
        },
        {
            "uuid": "b516d1d18261467bbb6f447f0c111be7",
            "time": 102166,
            "type": "nether.root"
        },
        {
            "uuid": "34c876e4a23a4fe5a1fbf76a41db0e78",
            "time": 96768,
            "type": "story.enter_the_nether"
        },
        {
            "uuid": "34c876e4a23a4fe5a1fbf76a41db0e78",
            "time": 96651,
            "type": "nether.root"
        },
        {
            "uuid": "b516d1d18261467bbb6f447f0c111be7",
            "time": 67970,
            "type": "adventure.root"
        },
        {
            "uuid": "34c876e4a23a4fe5a1fbf76a41db0e78",
            "time": 54942,
            "type": "story.mine_stone"
        },
        {
            "uuid": "34c876e4a23a4fe5a1fbf76a41db0e78",
            "time": 52439,
            "type": "story.iron_tools"
        },
        {
            "uuid": "34c876e4a23a4fe5a1fbf76a41db0e78",
            "time": 47906,
            "type": "story.root"
        },
        {
            "uuid": "b516d1d18261467bbb6f447f0c111be7",
            "time": 36321,
            "type": "story.mine_stone"
        },
        {
            "uuid": "b516d1d18261467bbb6f447f0c111be7",
            "time": 32315,
            "type": "story.iron_tools"
        },
        {
            "uuid": "b516d1d18261467bbb6f447f0c111be7",
            "time": 29515,
            "type": "story.smelt_iron"
        },
        {
            "uuid": "b516d1d18261467bbb6f447f0c111be7",
            "time": 27236,
            "type": "story.root"
        },
        {
            "uuid": "34c876e4a23a4fe5a1fbf76a41db0e78",
            "time": 23124,
            "type": "adventure.root"
        },
        {
            "uuid": "b516d1d18261467bbb6f447f0c111be7",
            "time": 8821,
            "type": "story.form_obsidian"
        },
        {
            "uuid": "34c876e4a23a4fe5a1fbf76a41db0e78",
            "time": 8697,
            "type": "story.form_obsidian"
        }
    ],
    "beginner": false,
    "season": 8,
    "date": 1748276394,
    "seedType": "RUINED_PORTAL",
    "bastionType": "STABLES",
    "tag": null,
    "replayExist": true
}