{
    "id": 2269062,
    "type": 2,
    "seed": {
        "id": "m7237pd89xbjdanb",
        "overworld": "SHIPWRECK",
        "nether": "TREASURE",
        "endTowers": [
            100,
            88,
            85,
            82
        ],
        "variations": [
            "biome:structure:deep_ocean",
            "type:structure:sideways",
            "biome:structure:deep_ocean",
            "type:structure:sideways",
            "biome:bastion:soul_sand_valley",
            "biome:fortress:soul_sand_valley",
            "end_tower:caged:back_center"
        ]
    },
    "category": "ANY",
    "gameMode": "default",
    "players": [
        {
            "uuid": "9fcde5d554ff4c20bd35505e67d21e86",
            "nickname": "Bigchillxyz",
            "roleType": 0,
            "eloRate": 1403,
            "eloRank": 336,
            "country": null
        },
        {
            "uuid": "34c876e4a23a4fe5a1fbf76a41db0e78",
            "nickname": "LazarBim",
            "roleType": 0,
            "eloRate": 1522,
            "eloRank": 185,
            "country": "us"
        }
    ],
    "spectators": [],
    "result": {
        "uuid": "34c876e4a23a4fe5a1fbf76a41db0e78",
        "time": 640185
    },
    "forfeited": false,
    "decayed": false,
    "rank": {
        "season": null,
        "allTime": null
    },
    "vod": [],
    "changes": [
        {
            "uuid": "34c876e4a23a4fe5a1fbf76a41db0e78",
            "change": 15,
            "eloRate": 1603
        },
        {
            "uuid": "9fcde5d554ff4c20bd35505e67d21e86",
            "change": -15,
            "eloRate": 1456
        }
    ],
    "completions": [
        {
            "uuid": "34c876e4a23a4fe5a1fbf76a41db0e78",
            "time": 640185
        }
    ],
    "timelines": [
        {
            "uuid": "34c876e4a23a4fe5a1fbf76a41db0e78",
            "time": 630085,
            "type": "projectelo.timeline.dragon_death"
        },
        {
            "uuid": "34c876e4a23a4fe5a1fbf76a41db0e78",
            "time": 615234,
            "type": "end.kill_dragon"
        },
        {
            "uuid": "34c876e4a23a4fe5a1fbf76a41db0e78",
            "time": 608436,
            "type": "adventure.shoot_arrow"
        },
        {
            "uuid": "34c876e4a23a4fe5a1fbf76a41db0e78",
            "time": 588895,
            "type": "end.root"
        },
        {
            "uuid": "34c876e4a23a4fe5a1fbf76a41db0e78",
            "time": 588895,
            "type": "story.enter_the_end"
        },
        {
            "uuid": "9fcde5d554ff4c20bd35505e67d21e86",
            "time": 534857,
            "type": "end.root"
        },
        {
            "uuid": "9fcde5d554ff4c20bd35505e67d21e86",
            "time": 534772,
            "type": "story.enter_the_end"
        },
        {
            "uuid": "34c876e4a23a4fe5a1fbf76a41db0e78",
            "time": 516892,
            "type": "story.follow_ender_eye"
        },
        {
            "uuid": "9fcde5d554ff4c20bd35505e67d21e86",
            "time": 482215,
            "type": "story.follow_ender_eye"
        },
        {
            "uuid": "9fcde5d554ff4c20bd35505e67d21e86",
            "time": 379533,
            "type": "projectelo.timeline.blind_travel"
        },
        {
            "uuid": "34c876e4a23a4fe5a1fbf76a41db0e78",
            "time": 373832,
            "type": "projectelo.timeline.blind_travel"
        },
        {
            "uuid": "9fcde5d554ff4c20bd35505e67d21e86",
            "time": 314852,
            "type": "nether.obtain_blaze_rod"
        },
        {
            "uuid": "9fcde5d554ff4c20bd35505e67d21e86",
            "time": 314233,
            "type": "adventure.root"
        },
        {
            "uuid": "9fcde5d554ff4c20bd35505e67d21e86",
            "time": 314083,
            "type": "adventure.kill_a_mob"
        },
        {
            "uuid": "34c876e4a23a4fe5a1fbf76a41db0e78",
            "time": 309660,
            "type": "nether.obtain_blaze_rod"
        },
        {
            "uuid": "34c876e4a23a4fe5a1fbf76a41db0e78",
            "time": 308010,
            "type": "nether.find_fortress"
        },
        {
            "uuid": "34c876e4a23a4fe5a1fbf76a41db0e78",
            "time": 305927,
            "type": "adventure.root"
        },
        {
            "uuid": "34c876e4a23a4fe5a1fbf76a41db0e78",
            "time": 305810,
            "type": "adventure.kill_a_mob"
        },
        {
            "uuid": "9fcde5d554ff4c20bd35505e67d21e86",
            "time": 305017,
            "type": "nether.find_fortress"
        },
        {
            "uuid": "9fcde5d554ff4c20bd35505e67d21e86",
            "time": 228766,
            "type": "nether.loot_bastion"
        },
        {
            "uuid": "34c876e4a23a4fe5a1fbf76a41db0e78",
            "time": 220322,
            "type": "nether.loot_bastion"
        },
        {
            "uuid": "9fcde5d554ff4c20bd35505e67d21e86",
            "time": 220061,
            "type": "nether.obtain_crying_obsidian"
        },
        {
            "uuid": "9fcde5d554ff4c20bd35505e67d21e86",
            "time": 219968,
            "type": "story.form_obsidian"
        },
        {
            "uuid": "34c876e4a23a4fe5a1fbf76a41db0e78",
            "time": 217185,
            "type": "nether.obtain_crying_obsidian"
        },
        {
            "uuid": "34c876e4a23a4fe5a1fbf76a41db0e78",
            "time": 217066,
            "type": "story.form_obsidian"
        },
        {
            "uuid": "9fcde5d554ff4c20bd35505e67d21e86",
            "time": 213580,
            "type": "husbandry.root"
        },
        {
            "uuid": "34c876e4a23a4fe5a1fbf76a41db0e78",
            "time": 184918,
            "type": "husbandry.root"
        },
        {
            "uuid": "9fcde5d554ff4c20bd35505e67d21e86",
            "time": 146610,
            "type": "nether.distract_piglin"
        },
        {
            "uuid": "34c876e4a23a4fe5a1fbf76a41db0e78",
            "time": 140370,
            "type": "nether.distract_piglin"
        },
        {
            "uuid": "9fcde5d554ff4c20bd35505e67d21e86",
            "time": 128016,
            "type": "nether.find_bastion"
        },
        {
            "uuid": "34c876e4a23a4fe5a1fbf76a41db0e78",
            "time": 124021,
            "type": "nether.find_bastion"
        },
        {
            "uuid": "9fcde5d554ff4c20bd35505e67d21e86",
            "time": 101437,
            "type": "nether.root"
        },
        {
            "uuid": "9fcde5d554ff4c20bd35505e67d21e86",
            "time": 101348,
            "type": "story.enter_the_nether"
        },
        {
            "uuid": "9fcde5d554ff4c20bd35505e67d21e86",
            "time": 97969,
            "type": "story.mine_stone"
        },
        {
            "uuid": "34c876e4a23a4fe5a1fbf76a41db0e78",
            "time": 96644,
            "type": "story.enter_the_nether"
        },
        {
            "uuid": "34c876e4a23a4fe5a1fbf76a41db0e78",
            "time": 96525,
            "type": "nether.root"
        },
        {
            "uuid": "34c876e4a23a4fe5a1fbf76a41db0e78",
            "time": 93424,
            "type": "story.mine_stone"
        },
        {
            "uuid": "9fcde5d554ff4c20bd35505e67d21e86",
            "time": 88561,
            "type": "story.lava_bucket"
        },
        {
            "uuid": "34c876e4a23a4fe5a1fbf76a41db0e78",
            "time": 86469,
            "type": "story.lava_bucket"
        },
        {
            "uuid": "9fcde5d554ff4c20bd35505e67d21e86",
            "time": 48468,
            "type": "story.iron_tools"
        },
        {
            "uuid": "9fcde5d554ff4c20bd35505e67d21e86",
            "time": 41736,
            "type": "story.root"
        },
        {
            "uuid": "34c876e4a23a4fe5a1fbf76a41db0e78",
            "time": 41724,
            "type": "story.iron_tools"
        },
        {
            "uuid": "34c876e4a23a4fe5a1fbf76a41db0e78",
            "time": 32979,
            "type": "story.root"
        },
        {
            "uuid": "34c876e4a23a4fe5a1fbf76a41db0e78",
            "time": 17292,
            "type": "story.smelt_iron"
        },
        {
            "uuid": "34c876e4a23a4fe5a1fbf76a41db0e78",
            "time": 17174,
            "type": "story.mine_diamond"
        },
        {
            "uuid": "9fcde5d554ff4c20bd35505e67d21e86",
            "time": 13843,
            "type": "story.smelt_iron"
        },
        {
            "uuid": "9fcde5d554ff4c20bd35505e67d21e86",
            "time": 13766,
            "type": "story.mine_diamond"
        }
    ],
    "beginner": false,
    "season": 8,
    "date": 1749084510,
    "seedType": "SHIPWRECK",
    "bastionType": "TREASURE",
    "tag": null,
    "replayExist": true
}